podunk/__init__.py
podunk/media/fonts/DejaVuSansMono/DejaVuSansMono-Bold.afm
podunk/media/fonts/DejaVuSansMono/DejaVuSansMono-Bold.pfb
podunk/media/fonts/DejaVuSansMono/DejaVuSansMono-BoldOblique.afm
podunk/media/fonts/DejaVuSansMono/DejaVuSansMono-BoldOblique.pfb
podunk/media/fonts/DejaVuSansMono/DejaVuSansMono-Oblique.afm
podunk/media/fonts/DejaVuSansMono/DejaVuSansMono-Oblique.pfb
podunk/media/fonts/DejaVuSansMono/DejaVuSansMono.afm
podunk/media/fonts/DejaVuSansMono/DejaVuSansMono.pfb
podunk/media/fonts/DejaVuSansMono/dejavu-fonts-mono-ttf-2.25.tar.gz
podunk/media/fonts/Gentium/GentiumBasic-Bold.afm
podunk/media/fonts/Gentium/GentiumBasic-Bold.pfb
podunk/media/fonts/Gentium/GentiumBasic-BoldItalic.afm
podunk/media/fonts/Gentium/GentiumBasic-BoldItalic.pfb
podunk/media/fonts/Gentium/GentiumBasic-Italic.afm
podunk/media/fonts/Gentium/GentiumBasic-Italic.pfb
podunk/media/fonts/Gentium/GentiumBasic.afm
podunk/media/fonts/Gentium/GentiumBasic.pfb
podunk/media/fonts/Gentium/GentiumBasic_110.zip
podunk/prefab/__init__.py
podunk/prefab/alignment.py
podunk/prefab/boxes.py
podunk/prefab/color.py
podunk/prefab/fields.py
podunk/prefab/fonts.py
podunk/prefab/formats.py
podunk/prefab/line.py
podunk/prefab/paper.py
podunk/prefab/styles.py
podunk/project/__init__.py
podunk/project/report.py
podunk/widget/__init__.py
podunk/widget/box.py
podunk/widget/column.py
podunk/widget/field.py
podunk/widget/font.py
podunk/widget/heading.py
podunk/widget/style.py
podunk/widget/table.py
podunk-0.9.1.dist-info/LICENSE
podunk-0.9.1.dist-info/METADATA
podunk-0.9.1.dist-info/WHEEL
podunk-0.9.1.dist-info/top_level.txt
podunk-0.9.1.dist-info/RECORD
