Metadata-Version: 2.1
Name: podunk
Version: 0.9.1
Summary: A simple library for creating tabular PDF reports in Python using the ReportLab PDF library
Home-page: https://github.com/torsten-pf/podunk
Author: Jim Storch
License: New BSD License
Project-URL: Bug Reports, https://github.com/torsten-pf/podunk/issues
Project-URL: Funding, https://donate.pypi.org
Project-URL: Source, https://github.com/torsten-pf/podunk/
Keywords: sample,setuptools,development
Platform: any
Classifier: Development Status :: 4 - Beta
Classifier: Intended Audience :: Developers
Classifier: Topic :: Software Development :: Build Tools
Classifier: License :: OSI Approved :: BSD License
Classifier: Programming Language :: Python :: 3
Classifier: Programming Language :: Python :: 3.6
Classifier: Programming Language :: Python :: 3.7
Classifier: Programming Language :: Python :: 3.8
Classifier: Programming Language :: Python :: 3.9
Classifier: Programming Language :: Python :: 3.10
Classifier: Programming Language :: Python :: 3 :: Only
Requires-Python: >=3.6, <4
License-File: LICENSE
Requires-Dist: reportlab
